ctorrepr.py
ctorrepr-0.1.2.dist-info/DESCRIPTION.rst
ctorrepr-0.1.2.dist-info/METADATA
ctorrepr-0.1.2.dist-info/RECORD
ctorrepr-0.1.2.dist-info/WHEEL
ctorrepr-0.1.2.dist-info/metadata.json
ctorrepr-0.1.2.dist-info/top_level.txt
