Metadata-Version: 2.0
Name: ctorrepr
Version: 0.1.2
Summary: A mix-in that provides __repr__() from constructor arguments.
Home-page: https://github.com/astralblue/ctorrepr
Author: Eugene M. Kim
Author-email: astralblue@gmail.com
License: MIT license
Keywords: ctorrepr
Platform: UNKNOWN
Classifier: Development Status :: 2 - Pre-Alpha
Classifier: Intended Audience :: Developers
Classifier: License :: OSI Approved :: MIT License
Classifier: Natural Language :: English
Classifier: Programming Language :: Python :: 2
Classifier: Programming Language :: Python :: 2.7
Classifier: Programming Language :: Python :: 3
Classifier: Programming Language :: Python :: 3.3
Classifier: Programming Language :: Python :: 3.4
Classifier: Programming Language :: Python :: 3.5
Classifier: Programming Language :: Python :: 3.6
